{
  "required": true,
  "package": "net.mafuyu33.mafishmod.mixin",
  "compatibilityLevel": "JAVA_17",
  "mixins": [
    "enchantmentblockmixin.custom.bellknockbackandhurt.BellBlockEntityMixin",
    "enchantmentitemmixin.ArmorEnchantmentMixin",
    "itemmixin.BowDashMixin",
    "itemmixin.MathModeMixin",
    "itemmixin.ShieldDashMixin",
    "itemmixin.ThrowableDiamondMixin"
  ],
  "client": [
    "ParticleManagerMixin",
    "enchantmentitemmixin.slippery.InventoryScreenMixin",
    "itemmixin.rubystuffrenderer.ItemRendererAccessor",
    "itemmixin.rubystuffrenderer.ItemRendererMixin",
    "itemmixin.rubystuffrenderer.ModelLoaderMixin",

    "enchantmentitemmixin.slippery.HandledScreenMixin",

  ],
  "injectors": {
    "defaultRequire": 1
	}
}